{"name":"Irene Cabading","settings":{"option1":true,"option2":true},"data":{"artists":[{"id":"Sy3XqkJ5-","name":"test"},{"id":"r11VIo19-","name":"asdfasdf"},{"id":"ry4iIjy9-","name":"The Weeknd","albums":[]},{"id":"BJyPvjycb","name":"Eminem","albums":["\"Recovery\" (2010)"]},{"id":"HyMuDjkcb","name":"Lloyd Banks","albums":["\"Mo Money In The Bank (Part Five The Final Chapter): Ganggreen Season Continues\" (2006)"]},{"id":"ByfZ3Y79-","name":"4444"},{"id":"H1QD2FQcW","name":"5555"},{"id":"BJvPnt7qZ","name":"5555asdfa"},{"id":"SyGHDRQqZ","name":"asdf"},{"id":"r1qcOC75Z","name":"555"},{"id":"Bk62sAXq-","name":"sdfasasdfasd"},{"id":"ryEjLQSqb","name":"Gloc-9","albums":["\"MKNM: Mga Kwento Ng Makata\" (2012)"]}],"albums":[],"songs":[{"id":"HyxnmckyqZ","name":"test","artist":"test","albums":[],"lyrics":"etwtasfsdf"},{"id":"SylkNIskqZ","name":"asdfasdf","artist":"asdfasdf","albums":[],"lyrics":"asdfasdfasdfasdfsadfasdfasdf"},{"id":"Skg4iLjkcZ","name":"\"The Hills (Eminem Remix)\"","artist":"The Weeknd","albums":[],"lyrics":"\n<!-- Usage of azlyrics.com content by any third-party lyrics provider is prohibited by our licensing agreement. Sorry about that. -->\n<i>[Eminem:]</i><br>\nSaid you want a little company<br>\nAnd I love it cause the thrill's cheap<br>\nSaid you left him for good this time<br>\nStill if he knew I was here, he'd wanna kill me<br>\nBut it's time you met the real me, filthy<br>\nBut wasn't always, will be<br>\nYour pill refill, feeling I'll still be<br>\nYour addiction, you can touch a prescription, but don't fill me<br>\nI let you see my dark side, but like a mic check, you got one too<br>\nSo when the sparks fly, we hit the flight deck and got sprung, pew<br>\nLike an ejector seat, from an F-15<br>\nBut tonight we don't need those pills, just the effects of each other<br>\nBut we gon' film cause I will want your ex to see<br>\n(Get it?) that...<br>\n<br>\nI only call you when it's half past five<br>\nThe only time that I'll be by your side<br>\nI only love it when you touch me, not feel me<br>\nWhen I'm fucked up, that's the real me<br>\nWhen I'm fucked up, that's the real me, yeah<br>\nI only fuck you when it's half past five<br>\nThe only time I'd ever call you mine<br>\nI only love it when you touch me, not feel me<br>\nWhen I'm fucked up, that's the real me<br>\nWhen I'm fucked up, that's the real me, babe<br>\n<br>\n<i>[Eminem:]</i><br>\nAnd every time he hurt you, I heard you<br>\nYour shoulder to cry on<br>\nAnd I'll be damned if I weren't who you turned to<br>\nYou said he drove you to my arms<br>\nBut don't you know, remember when I told you<br>\nI would never let down my guard<br>\nAnd I hope you feel like dirt when I hold you<br>\nCause is it really over?<br>\nBut you just want a little company<br>\nAnd you just really wanna thrill seek<br>\nSaid you left him for good this time<br>\nBullshit, what your friends do, spill beans?<br>\nOr you just wanna be guilt free and still creep<br>\nBut these hills see, from that POV<br>\nWe can touch but the only way you'll feel me<br>\nIs with a camera, film me<br>\nYou're nothing but a barfly<br>\nYou got your sights set on the one who you run to<br>\nBut I'm a far cry from what you might get, if we come true<br>\nSo keep texting me, but at night, if you seek those thrills<br>\nWhat I expect to be?<br>\nCause if you cheat on him just means I will be the next to be<br>\nYour ex, so no complexities, just sex<br>\nAnd don't lecture me, just accept that...<br>\n<br>\nI only call you when it's half past five<br>\nThe only time that I'll be by your side<br>\nI only love it when you touch me, not feel me<br>\nWhen I'm fucked up, that's the real me<br>\nWhen I'm fucked up, that's the real me, yeah<br>\nI only fuck you when it's half past five<br>\nThe only time I'd ever call you mine<br>\nI only love it when you touch me, not feel me<br>\nWhen I'm fucked up, that's the real me<br>\nWhen I'm fucked up, that's the real me, babe<br>\n<br>\nHills have eyes, the hills have voice<br>\nWho are you to judge, who are you to judge?<br>\nHide your lies, girl, hide your lies<br>\nOnly you to trust, only you<br>\n<br>\nI only call you when it's half past five<br>\nThe only time that I'll be by your side<br>\nI only love it when you touch me, not feel me<br>\nWhen I'm fucked up, that's the real me<br>\nWhen I'm fucked up, that's the real me, yeah<br>\nI only fuck you when it's half past five<br>\nThe only time I'd ever call you mine<br>\nI only love it when you touch me, not feel me<br>\nWhen I'm fucked up, that's the real me<br>\nWhen I'm fucked up, that's the real me, babe<br>\n<br>\nEwedihalehu<br>\nYene konjo, ewedihalehu<br>\nYene fikir, fikir, fikir, fikir<br>\nYene fikir, fikir, fikir, fikir\n"},{"id":"rklJvvsJqZ","name":"\"Love The Way You Lie\"","artist":"Eminem","albums":["\"Recovery\" (2010)"],"lyrics":"\n<!-- Usage of azlyrics.com content by any third-party lyrics provider is prohibited by our licensing agreement. Sorry about that. -->\n<i>[Intro - Rihanna:]</i><br>\nJust gonna stand there and watch me burn<br>\nBut that's alright because I like the way it hurts<br>\nJust gonna stand there and hear me cry<br>\nBut that's alright because I love the way you lie<br>\nI love the way you lie<br>\n<br>\n<i>[Verse - Eminem:]</i><br>\nI can't tell you what it really is<br>\nI can only tell you what it feels like<br>\nAnd right now there's a steel knife in my windpipe<br>\nI can't breathe but I still fight while I can fight<br>\nAs long as the wrong feels right it's like I'm in flight<br>\nHigh off her love, drunk from her hate,<br>\nIt's like I'm huffing paint and I love her the more I suffer, I suffocate<br>\nAnd right before I'm about to drown, she resuscitates me<br>\nShe fucking hates me and I love it.<br>\n\"Wait! Where you going?\"<br>\n\"I'm leaving you!\"<br>\n\"No you ain't. Come back.\"<br>\nWe're running right back.<br>\nHere we go again<br>\nIt's so insane cause when it's going good, it's going great<br>\nI'm Superman with the wind at his back, she's Lois Lane<br>\nBut when it's bad it's awful, I feel so ashamed I snapped<br>\nWho's that dude?<br>\n\"I don't even know his name.\"<br>\nI laid hands on her, I'll never stoop so low again<br>\nI guess I don't know my own strength<br>\n<br>\n<i>[Chorus - Rihanna:]</i><br>\nJust gonna stand there and watch me burn<br>\nBut that's alright because I like the way it hurts<br>\nJust gonna stand there and hear me cry<br>\nBut that's alright because I love the way you lie<br>\nI love the way you lie<br>\nI love the way you lie<br>\n<br>\n<i>[Verse - Eminem:]</i><br>\nYou ever love somebody so much you can barely breathe when you're with 'em<br>\nYou meet and neither one of you even know what hit 'em<br>\nGot that warm fuzzy feeling<br>\nYeah, them chills you used to get 'em<br>\nNow you're getting fucking sick of looking at 'em<br>\nYou swore you'd never hit 'em; never do nothing to hurt 'em<br>\nNow you're in each other's face spewing venom in your words when you spit them<br>\nYou push, pull each other's hair, scratch, claw, bit 'em<br>\nThrow 'em down, pin 'em<br>\nSo lost in the moments when you're in them<br>\nIt's the rage that took over,<br>\nIt controls you both<br>\nSo they say you're best to go your separate ways<br>\nGuess that they don't know you 'cause today that was yesterday<br>\nYesterday is over, it's a different day<br>\nSound like broken records playing over but you promised her<br>\nNext time you show restraint<br>\nYou don't get another chance<br>\nLife is no Nintendo game<br>\nBut you lied again<br>\nNow you get to watch her leave out the window<br>\nGuess that's why they call it window pane<br>\n<br>\n<i>[Chorus - Rihanna:]</i><br>\nJust gonna stand there and watch me burn<br>\nBut that's alright because I like the way it hurts<br>\nJust gonna stand there and hear me cry<br>\nBut that's alright because I love the way you lie<br>\nI love the way you lie<br>\nI love the way you lie<br>\n<br>\n<i>[Verse - Eminem:]</i><br>\nNow I know we said things, did things that we didn't mean<br>\nAnd we fall back into the same patterns, same routine<br>\nBut your temper's just as bad as mine is<br>\nYou're the same as me<br>\nWhen it comes to love you're just as blinded<br>\nBaby, please come back<br>\nIt wasn't you, baby it was me<br>\nMaybe our relationship isn't as crazy as it seems<br>\nMaybe that's what happens when a tornado meets a volcano<br>\nAll I know is I love you too much to walk away though<br>\nCome inside, pick up your bags off the sidewalk<br>\nDon't you hear sincerity in my voice when I talk<br>\nTold you this is my fault<br>\nLook me in the eyeball<br>\nNext time I'm pissed, I'll aim my fist at the drywall<br>\nNext time? There won't be no next time!<br>\nI apologize even though I know its lies<br>\nI'm tired of the games I just want her back<br>\nI know I'm a liar<br>\nIf she ever tries to fucking leave again<br>\nIm'a tie her to the bed and set this house on fire<br>\nI'm just gonna<br>\n<br>\n<i>[Outro - Rihanna:]</i><br>\nJust gonna stand there and watch me burn<br>\nBut that's alright because I like the way it hurts<br>\nJust gonna stand there and hear me cry<br>\nBut that's alright because I love the way you lie<br>\nI love the way you lie<br>\nI love the way you lie\n"},{"id":"rkeGdwjk5W","name":"\"Eminem - Speaks (Interlude)\"","artist":"Lloyd Banks","albums":["\"Mo Money In The Bank (Part Five The Final Chapter): Ganggreen Season Continues\" (2006)"],"lyrics":"\n<!-- Usage of azlyrics.com content by any third-party lyrics provider is prohibited by our licensing agreement. Sorry about that. -->\n<i>[Eminem:]</i> You know Ca$his, Obie, D12 all we are down on the line! Bobby Creek'! Like... that's one of the requiermants of... havin' to get... on Shady Records or G-Unit Records, youkno'msayin'? Or Aftermath... is you gotta be able to RAP!<br>\n<i>[Man 1:]</i> Yeah, oh yeah!<br>\n<i>[Man 2:]</i> Can't forget, can't forget Lloyd Bank$!<br>\n<i>[Man 1:]</i> Oh, The PunchLine King!<br>\n<i>[Man 2:]</i> Yeah!<br>\n<i>[Man 1:]</i> The PunchLine King!<br>\n<i>[Eminem:]</i> Bank$, too...<br>\n<i>[Man 1:]</i> Young Buck!<br>\n<i>[Eminem:]</i><br>\nBank$ too, Young Buck, like... it's an, it's a' requiermant, it's like... it's...<br>\nThey would, they would... not be in the camp! None of us would be in the camp, if we didn't have to, to... SHOWIN' PROOF!<br>\n<i>[Man 2:]</i> Exactly!<br>\n<i>[Man 1:]</i> Yeah.<br>\n<i>[Eminem:]</i> Youkno'msayin'? And the way the game is now... it's like everybody and their brother and their mother and their brother's mother's cousin... CAN RAP! An' it's accepted, people are... are, they ACCEPTIN' IT! <i>[echoes]</i>\n"},{"id":"HyeGZ3K7cZ","name":"4444","artist":"4444","albums":[],"lyrics":"444444"},{"id":"HklQv3F79b","name":"5555","artist":"5555","albums":[],"lyrics":"5555555"},{"id":"BygwDntmcb","name":"5555adf","artist":"5555asdfa","albums":[],"lyrics":"5555555"},{"id":"SkgGrvA7qb","name":"asdf","artist":"asdf","albums":[],"lyrics":"asdf"},{"id":"Syg55_C7cW","name":"555555555","artist":"555","albums":[],"lyrics":"55555"},{"id":"B1xpniR7cZ","name":"asdfasdfasdf","artist":"sdfasasdfasd","albums":[],"lyrics":"asdfasdfasdfasdfasdf"},{"id":"ryri4fH5W","name":"\"25 To Life\"","artist":"Eminem","albums":["\"Recovery\" (2010)"],"lyrics":"\n<!-- Usage of azlyrics.com content by any third-party lyrics provider is prohibited by our licensing agreement. Sorry about that. -->\n<i>[Intro]</i><br>\nToo late for the other side<br>\nCaught in a chase<br>\n25 to life<br>\nToo late for the other side<br>\nCaught in a chase<br>\n25 to life<br>\n(<i>[Eminem:]</i> Yeah)<br>\nToo late<br>\n(<i>[Eminem:]</i> I can't keep chasing em<br>\nI'm taking my life back)<br>\nCaught in a chase<br>\n25 to life<br>\n<br>\n<i>[Verse 1]</i><br>\nI don't think she understands the sacrifices that I made<br>\nMaybe if this bitch had acted right I would've stayed<br>\nBut I've already wasted over half of my life I would've laid<br>\nDown and died for you I no longer cry for you<br>\nNo more pain bitch you<br>\nTook me for granted took my heart and ran it straight into the planet<br>\nInto the dirt I can no longer stand it<br>\nNow my respect I demand it<br>\nImma take control of this relationship<br>\nCommand it, and imma be the boss of you now goddamnit<br>\nAnd what I mean is that I will no longer let you control me<br>\nSo you better hear me out this much you owe me<br>\nI gave up my life for you, totally devoted to you while I've stayed<br>\nFaithful all the way this is how I fucking get repaid<br>\nLook at how I dress fucking baggy sweats, go to work a mess<br>\nAlways in a rush to get back to you I ain't heard you yet<br>\nNot even once say you appreciate me I deserve respect<br>\nI've done my best to give you nothing less than perfectness<br>\nAnd I know that if I end this I'll no longer have nothing left<br>\nBut you keep treating me like a staircase it's time to fucking step<br>\nAnd I wont be coming back so don't hold your fucking breath<br>\nYou know what you've done no need to go in depth<br>\nI told you, you'd be sorry if I fucking left<br>\nI'd laugh while you wept<br>\nHows it feel now, yeah, funny ain't it, you neglected me<br>\nDid me a favor although my spirit free you've set<br>\nBut a special place for you in my heart I have kept<br>\nIt's unfortunate but it's,<br>\n<br>\n<i>[Chorus]</i><br>\nToo late for the other side (<i>[Eminem:]</i> Yeah)<br>\nCaught in a chase<br>\n25 to life<br>\n(<i>[Eminem:]</i> Can't take no more)<br>\nToo late for the other side<br>\nCaught in a chase<br>\n25 to life<br>\n<br>\n<i>[Verse 2]</i><br>\nI feel like when I bend over backwards for you all you do is laugh<br>\nCause that ain't good enough you expect me to fold myself in half<br>\nTil I snap<br>\nDon't think I'm loyal<br>\nAll I do is rap<br>\nHow can I moonlight on the side<br>\nI have no life outside of that<br>\nDon't I give you enough of my time<br>\nYou don't think so, do you?<br>\nJealous when I spend time with the girls<br>\nWhy I'm married to you still man I don't know<br>\nBut tonight I'm serving you with papers<br>\nI'm divorcing you<br>\nGo marry someone else and make em famous<br>\nAnd take away their freedom like you did to me<br>\nTreat em like you don't need them and they ain't worthy of you<br>\nFeed em the same shit that you made me eat<br>\nI'm moving on forget you oh,<br>\nNow I'm special? I didn't feel special when I was with you<br>\nAll I ever felt was this<br>\nHelplessness<br>\nImprisoned by a selfish bitch<br>\nChew me up and spit me out<br>\nI fell for this so many times<br>\nIt's ridiculous<br>\nAnd still I stick with this<br>\nI'm sick of this but in my sickness and addiction<br>\nYou're addictive as they get<br>\nEvil as they come vindictive as they make em<br>\nMy friends keep asking me why I can't just walk away from<br>\nI'm addicted<br>\nTo the pain, the stress, the drama<br>\nI'm drawn in so I guess imma mess<br>\nCursed and blessed<br>\nBut this time imma<br>\nAin't changing my mind<br>\nI'm climbing out this abyss<br>\nYou screaming as I walk out that I'll be missed<br>\nBut when you spoke of people who meant the most to you<br>\nYou left me off your list<br>\n<br>\nFuck you hip-hop<br>\nI'm leaving you, my life sentence is served bitch<br>\nAnd it's just<br>\n<br>\n<i>[Chorus]</i><br>\nToo late for the other side<br>\nCaught in a chase<br>\n25 to life<br>\n(<i>[Eminem:]</i> I'm gone, man)<br>\nToo late for the other side<br>\nCaught in a chase<br>\n25 to life<br>\nToo late<br>\nCaught in a chase<br>\n25 to life\n"},{"id":"HJBKUQr9-","name":"\"Rap God\"","artist":"Eminem","albums":["\"The Marshall Mathers LP 2\" (2013)"],"lyrics":"\n<!-- Usage of azlyrics.com content by any third-party lyrics provider is prohibited by our licensing agreement. Sorry about that. -->\nLook, I was gonna go easy on you not to hurt your feelings<br>\nBut I'm only going to get this one chance<br>\n(Six minutes, six minutes)<br>\nSomething's wrong, I can feel it<br>\n(Six minutes, six minutes, Slim Shady, you're on)<br>\nJust a feeling I've got<br>\nLike something's about to happen<br>\nBut I don't know what<br>\nIf that means, what I think it means, we're in trouble<br>\nBig trouble. And if he is as bananas as you say<br>\nI'm not taking any chances<br>\nYou are just what the doc ordered<br>\n<br>\nI'm beginning to feel like a Rap God, Rap God<br>\nAll my people from the front to the back nod, back nod<br>\nNow who thinks their arms are long enough to slap box, slap box?<br>\nThey said I rap like a robot, so call me rap-bot<br>\n<br>\nBut for me to rap like a computer must be in my genes<br>\nI got a laptop in my back pocket<br>\nMy pen'll go off when I half-cock it<br>\nGot a fat knot from that rap profit<br>\nMade a living and a killing off it<br>\nEver since Bill Clinton was still in office<br>\nWith Monica Lewinski feeling on his nutsack<br>\nI'm an MC still as honest<br>\nBut as rude and as indecent as all hell<br>\nSyllables, skill-a-holic (Kill 'em all with)<br>\nThis flippity, dippity-hippity hip-hop<br>\nYou don't really wanna get into a pissing match<br>\nWith this rappity-rap<br>\nPacking a mack in the back of the Ac<br>\nbackpack rap, crap, yap-yap, yackety-yack<br>\nand at the exact same time<br>\nI attempt these lyrical acrobat stunts while I'm practicing that<br>\nI'll still be able to break a motherfuckin' table<br>\nOver the back of a couple of faggots and crack it in half<br>\nOnly realized it was ironic<br>\nI was signed to Aftermath after the fact<br>\nHow could I not blow? All I do is drop \"F\" bombs<br>\nFeel my wrath of attack<br>\nRappers are having a rough time period<br>\nHere's a maxi pad<br>\nIt's actually disastrously bad<br>\nFor the wack while I'm masterfully constructing this masterpiece yeah<br>\n<br>\n'Cause I'm beginning to feel like a Rap God, Rap God<br>\nAll my people from the front to the back nod, back nod<br>\nNow who thinks their arms are long enough to slap box, slap box?<br>\nLet me show you maintaining this shit ain't that hard, that hard<br>\n<br>\nEverybody want the key and the secret to rap<br>\nImmortality like I have got<br>\nWell, to be truthful the blueprint's<br>\nSimply rage and youthful exuberance<br>\nEverybody loves to root for a nuisance<br>\nHit the Earth like an asteroid<br>\nDid nothing but shoot for the moon since (PPEEYOOM)<br>\nMCs get taken to school with this music<br>\n'Cause I use it as a vehicle to 'bust a rhyme'<br>\nNow I lead a new school full of students<br>\nMe? I'm a product of Rakim<br>\nLakim Shabazz, 2Pac, N.W.A., Cube, hey, Doc, Ren<br>\nYella, Eazy, thank you, they got Slim<br>\nInspired enough to one day grow up<br>\nBlow up and be in a position<br>\nTo meet Run-D.M.C. and induct them<br>\nInto the motherfuckin' Rock n'<br>\nRoll Hall of Fame even though I walk in the church<br>\nAnd burst in a ball of flames<br>\nOnly Hall of Fame I'll be inducted in is the alcohol of fame<br>\nOn the wall of shame<br>\nYou fags think it's all a game<br>\n'Til I walk a flock of flames<br>\nOff a plank and<br>\nTell me what in the fuck are you thinking?<br>\nLittle gay-looking boy<br>\nSo gay I can barely say it with a 'straight' face, looking boy<br>\nYou're witnessing a mass-occur like you're watching a church gathering take place, looking boy<br>\nOy vey, that boy's gay<br>\nThat's all they say, looking boy<br>\nYou get a thumbs up, pat on the back<br>\nAnd a \"way to go\" from your label every day, looking boy<br>\nHey, looking boy, what d'you say, looking boy?<br>\nI get a \"hell yeah\" from Dre, looking boy<br>\nI'mma work for everything I have<br>\nNever asked nobody for shit<br>\nGet outta my face, looking boy<br>\nBasically boy you're never gonna be capable<br>\nof keeping up with the same pace, looking boy, 'cause<br>\n<br>\nI'm beginning to feel like a Rap God, Rap God<br>\nAll my people from the front to the back nod, back nod<br>\nThe way I'm racing around the track, call me Nascar, Nascar<br>\nDale Earnhardt of the trailer park, the White Trash God<br>\nKneel before General Zod this planet's Krypton, no Asgard, Asgard<br>\n<br>\nSo you'll be Thor and I'll be Odin<br>\nYou rodent, I'm omnipotent<br>\nLet off then I'm reloading<br>\nImmediately with these bombs I'm totin'<br>\nAnd I should not be woken<br>\nI'm the walking dead<br>\nBut I'm just a talking head, a zombie floating<br>\nBut I got your mom deep throating<br>\nI'm out my Ramen Noodle<br>\nWe have nothing in common, poodle<br>\nI'm a Doberman, pinch yourself<br>\nIn the arm and pay homage, pupil<br>\nIt's me<br>\nMy honesty's brutal<br>\nBut it's honestly futile if I don't utilize<br>\nWhat I do though for good<br>\nAt least once in a while so I wanna make sure<br>\nSomewhere in this chicken scratch I scribble and doodle<br>\nEnough rhymes to<br>\nMaybe try to help get some people through tough times<br>\nBut I gotta keep a few punchlines<br>\nJust in case 'cause even you unsigned<br>\nRappers are hungry looking at me like it's lunchtime<br>\nI know there was a time where once I<br>\nWas king of the underground<br>\nBut I still rap like I'm on my Pharoahe Monch grind<br>\nSo I crunch rhymes<br>\nBut sometimes when you combine<br>\nAppeal with the skin color of mine<br>\nYou get too big and here they come trying to<br>\nCensor you like that one line I said<br>\nOn \"I'm Back\" from the Mathers LP<br>\nOne when I tried to say I'll take seven kids from Columbine<br>\nPut 'em all in a line<br>\nAdd an AK-47, a revolver and a nine<br>\nSee if I get away with it now<br>\nThat I ain't as big as I was, but I'm<br>\nMorphin' into an immortal coming through the portal<br>\nYou're stuck in a time warp from two thousand four though<br>\nAnd I don't know what the fuck that you rhyme for<br>\nYou're pointless as Rapunzel<br>\nWith fucking cornrows<br>\nYou write normal? Fuck being normal<br>\nAnd I just bought a new ray gun from the future<br>\nJust to come and shoot ya<br>\nLike when Fabulous made Ray J mad<br>\n'Cause Fab said he looked like a fag<br>\nAt Mayweather's pad singin' to a man<br>\nWhile he play piano<br>\nMan, oh man, that was the 24/7 special<br>\nOn the cable channel<br>\nSo Ray J went straight to the radio station the very next day<br>\n\"Hey, Fab, I'mma kill you\"<br>\nLyrics coming at you with supersonic speed, (JJ Fad)<br>\nUh, summa lumma dooma lumma you assuming I'm a human<br>\nWhat I gotta do to get it through to you? I'm superhuman<br>\nInnovative and I'm made of rubber, so that anything you say is<br>\nRicocheting off of me and it'll glue to you<br>\nI'm devastating more than ever demonstrating<br>\nHow to give a motherfuckin' audience a feeling like it's levitating<br>\nNever fading, and I know that haters are forever waiting<br>\nFor the day that they can say I fell off, they'll be celebrating<br>\n'Cause I know the way to get 'em motivated<br>\nI make elevating music<br>\nYou make elevator music<br>\n\"Oh, he's too mainstream.\"<br>\nWell, that's what they do<br>\nWhen they get jealous, they confuse it<br>\n\"It's not hip-hop, it's pop.\"<br>\n'Cause I found a hella way to fuse it<br>\nWith rock, shock rap with Doc<br>\nThrow on \"Lose Yourself\" and make 'em lose it<br>\n\"I don't know how to make songs like that.<br>\nI don't know what words to use.\"<br>\nLet me know when it occurs to you<br>\nWhile I'm ripping any one of these verses that versus you<br>\nIt's curtains, I'm inadvertently hurtin' you<br>\nHow many verses I gotta murder to<br>\nProve that if you were half as nice,<br>\nyour songs you could sacrifice virgins to<br>\nUnghh, school flunky, pill junky<br>\nBut look at the accolades these skills brung me<br>\nFull of myself, but still hungry<br>\nI bully myself 'cause I make me do what I put my mind to<br>\nWhen I'm a million leagues above you<br>\nIll when I speak in tongues<br>\nBut it's still tongue-in-cheek, fuck you<br>\nI'm drunk. So, Satan, take the fucking wheel<br>\nI'm asleep in the front seat<br>\nBumping Heavy D and the Boyz<br>\nStill \"Chunky, but Funky\"<br>\nBut in my head there's something<br>\nI can feel tugging and struggling<br>\nAngels fight with devils and<br>\nHere's what they want from me<br>\nThey're asking me to eliminate some of the women hate<br>\nBut if you take into consideration the bitter hatred I had<br>\nThen you may be a little patient and more sympathetic to the situation<br>\nAnd understand the discrimination<br>\nBut fuck it<br>\nLife's handing you lemons<br>\nMake lemonade then<br>\nBut if I can't batter the women<br>\nHow the fuck am I supposed to bake them a cake then?<br>\nDon't mistake him for Satan<br>\nIt's a fatal mistake if you think I need to be overseas<br>\nAnd take a vacation to trip a broad<br>\nAnd make her fall on her face and<br>\nDon't be a retard, be a king?<br>\nThink not<br>\nWhy be a king when you can be a God?\n"},{"id":"Syl4jUmB9-","name":"\"Salarin\"","artist":"Gloc-9","albums":["\"MKNM: Mga Kwento Ng Makata\" (2012)"],"lyrics":"\n<!-- Usage of azlyrics.com content by any third-party lyrics provider is prohibited by our licensing agreement. Sorry about that. -->\n<i>[Chorus: Bamboo]</i><br>\nThe dates go on, we down for sure<br>\nBut on my own (Now tell me everything's all right)<br>\nI pay my own way, sold my soul<br>\nWe on the clock (You tell me name my price)<br>\nYou reap what you saw but that ain't what I see<br>\nWhatever happened to the promise we would've dreamed<br>\nI'll just do my time and take what's due me<br>\nWhen tomorrow comes, it's just another day<br>\n<br>\n<i>[Gloc 9:]</i><br>\nMga daliring nakaturo, dugo na tumutulo<br>\nPangalang nakasulat sa maputik na dipuho<br>\nKatanungan na mula pa sa ating mga ninuno<br>\nSaan ba ang daan bakit hindi niyo maituro<br>\nKaing-kaing na hinaing, daang-daang daing<br>\nAng lunas ba'y imposible parang dilat na bahing<br>\nLahat malinaw kahit bulag o mata'y nakapiring<br>\nParang ang daming doktor pero di gumagaling<br>\nAng bayan kong minamahal ganito na lamang ba<br>\nNa ang iyong kaunlara'y dinadaanan ng iba<br>\nSa kanila galing ang bigas, di ka ba nagtataka<br>\nBakit meron paring nagugutom na magsasaka<br>\nKamusmos ang nasa lansangan kayod kahit maalinsangan<br>\nPatuloy sa pagdami tila di nababawasan<br>\nAng problema teka kung gusto mo talagang malaman<br>\nAy sumama ka sa amin at subakan nating pagmasdan ang<br>\n<br>\n<i>[Chorus: Bamboo]</i><br>\nThe dates go on, we down for sure (Now tell me everything's all right)<br>\nI pay my own way, sold my soul (You tell me name my price)<br>\nYou reap what you saw but that ain't what I see<br>\nWhatever happened to the promise we would've dreamed<br>\nI'll just do my time and take what's due me<br>\nWhen tomorrow comes, it's just another day<br>\n<br>\n<i>[Gloc-9:]</i><br>\nSilang mga nagiging biktima tila dikit-dikit sila<br>\nLeeg na ginilit pinilipit kasi gipit sila<br>\nMakuha lang ang perang inipon sa alkansya<br>\nSa isang gisap mata pabilisang magpasya na ang<br>\n(You just don't see why I try)<br>\nSayo ay akin, at ang sa'kin ay akin palagi<br>\nGanyan ang buhay na parang buhol-buhol na tali<br>\nKailangang dumiskarte, kailangang makabawi<br>\nKakapit sa patalim walang baka-bakasakali<br>\nKasi walang trabaho makuha dun sa amin<br>\nAt bihirang mapahiran ng mantika ang pagkain<br>\nHindi naman ako kinukulang sa panalangin<br>\nO tinatamaan lamang ng aking suntok ay hangin<br>\nNgayo'y nakakulong pero matagal ko nang nalaman<br>\nNa ang katarungan daw ay para lang sa mayayaman<br>\nAng katotohanan ba ay gusto mong masilayan<br>\nHalika't sabay-sabay nating tingnan ang katibayan sa<br>\n<br>\n<i>[Chorus: Bamboo]</i><br>\nThe dates go on, we down for sure (Salamin)<br>\nHad my own way, sold this soul (Salarin)<br>\nYou reap what you saw but that ain't what I see<br>\nWhatever happened to the promise we would've dreamed<br>\nI'll just do my time and take what's due me<br>\nWhen tomorrow comes, it's just another day<br>\n<br>\nThe dates go on, we down for sure (Salamin)<br>\nI pay my own way, sold this soul (Salarin)<br>\nYou reap what you sow but that ain't what I see<br>\nWhatever happened to the promise we would've dreamed<br>\nI'll just do my time and take what's due to me<br>\nWhen tomorrow comes, it's just another day<br>\n<br>\n<i>[Bamboo:]</i><br>\nFight or fly, or will we simply fade away<br>\nTired of all the talking<br>\nWe're still singing the same old songs<br>\nYet things haven't changed<br>\nBayad ko buhay ko, ba't ganun (Bayad ko buhay ko, ba't ganun)<br>\nBayad ko buhay ko, ba't ganun (Bayad ko buhay ko, ba't ganun)<br>\nBayad ko buhay ko, ba't ganun (Bayad ko buhay ko, ba't ganun)<br>\nBayad ko buhay ko, ba't ganun<br>\n<br>\n<i>[Gloc-9:]</i><br>\nMama bayad bayad, utak kong sumayad<br>\nMalakas ang hangin baka nama'y walang layag<br>\nOo nang oo pero di naman pumapayag<br>\nMainit na tinapay na ang palaman ay amag<br>\nSa bayan na laging malakas ang mga bulong<br>\nKahit umusad ay tila di umiikot ang gulong<br>\nMga bulag at pipi ang gamit lang ay ilong<br>\nBakit nangangamoy bulok ang inyong mga barong<br>\n<br>\nMama bayad bayad, utak kong sumayad<br>\nMalakas ang hangin baka nama'y walang layag<br>\nOo nang oo pero di naman pumapayag<br>\nMainit na tinapay na ang palaman ay amag<br>\nSa bayan na laging malakas ang mga bulong<br>\nKahit umusad ay tila di umiikot ang gulong<br>\nMga bulag at pipi ang gamit lang ay ilong<br>\nBakit nangangamoy bulok ang inyong mga barong\n"}]}}
